pybuilder_docker_too/__init__.py
pybuilder_docker_too-46.dist-info/METADATA
pybuilder_docker_too-46.dist-info/WHEEL
pybuilder_docker_too-46.dist-info/namespace_packages.txt
pybuilder_docker_too-46.dist-info/top_level.txt
pybuilder_docker_too-46.dist-info/zip-safe
pybuilder_docker_too-46.dist-info/RECORD
